pycounts_jacqann/.ipynb_checkpoints/__init__-checkpoint.py
pycounts_jacqann/.ipynb_checkpoints/plotting-checkpoint.py
pycounts_jacqann/.ipynb_checkpoints/pycounts-checkpoint.py
pycounts_jacqann/__init__.py
pycounts_jacqann/plotting.py
pycounts_jacqann/pycounts.py
pycounts_jacqann-0.2.0.dist-info/LICENSE
pycounts_jacqann-0.2.0.dist-info/WHEEL
pycounts_jacqann-0.2.0.dist-info/METADATA
pycounts_jacqann-0.2.0.dist-info/RECORD
